check_swear/__init__.py
check_swear/data/__init__.py
check_swear/data/model.joblib
check_swear/data/vectorizer.joblib
check_swear/model_prep/__init__.py
check_swear/model_prep/tokenizer.py
check_swear/model_prep/words.json
check_swear/model_prep/words_prep.py
check_swear/swear_core/__init__.py
check_swear/swear_core/core.py
check_swear/swear_core/utils.py
check_swear-0.1.4.dist-info/METADATA
check_swear-0.1.4.dist-info/WHEEL
check_swear-0.1.4.dist-info/top_level.txt
check_swear-0.1.4.dist-info/RECORD
