Metadata-Version: 2.1
Name: check-swear
Version: 0.1.4
Summary: A profanity filter for Russian comments.
Home-page: UNKNOWN
Author: Daniil Kremnev
Author-email: legend.super567@gmail.com
License: UNKNOWN
Platform: UNKNOWN
Classifier: Programming Language :: Python :: 3.9
Classifier: Operating System :: OS Independent
Requires-Python: >=3.9
Requires-Dist: scikit-learn ==1.4.0
Requires-Dist: joblib ==1.3.2
Requires-Dist: nltk >=3.8.1
